[
  {
    "id": 101,
    "m": "0I",
    "coef1": 998,
    "coef2": 516,
    "coef3": 630,
    "coef4": 175,
    "coef5": 0,
    "coef6": 0,
    "Tipo": "interior"
  },
  {
    "id": 102,
    "m": "0II",
    "coef1": 1018,
    "coef2": 544,
    "coef3": 668,
    "coef4": 181,
    "coef5": 0,
    "coef6": 0,
    "Tipo": "interior"
  },
  {
    "id": 103,
    "m": "0.5I",
    "coef1": 553,
    "coef2": 409,
    "coef3": 312,
    "coef4": 139,
    "coef5": 0,
    "coef6": 0,
    "Tipo": "interior"
  },
  {
    "id": 104,
    "m": "0.5II",
    "coef1": 565,
    "coef2": 431,
    "coef3": 322,
    "coef4": 144,
    "coef5": 0,
    "coef6": 0,
    "Tipo": "interior"
  },
  {
    "id": 105,
    "m": "0.6I",
    "coef1": 489,
    "coef2": 391,
    "coef3": 268,
    "coef4": 134,
    "coef5": 0,
    "coef6": 0,
    "Tipo": "interior"
  },
  {
    "id": 106,
    "m": "0.6II",
    "coef1": 498,
    "coef2": 412,
    "coef3": 276,
    "coef4": 139,
    "coef5": 0,
    "coef6": 0,
    "Tipo": "interior"
  },
  {
    "id": 107,
    "m": "0.7I",
    "coef1": 432,
    "coef2": 371,
    "coef3": 228,
    "coef4": 130,
    "coef5": 0,
    "coef6": 0,
    "Tipo": "interior"
  },
  {
    "id": 108,
    "m": "0.7II",
    "coef1": 438,
    "coef2": 388,
    "coef3": 236,
    "coef4": 135,
    "coef5": 0,
    "coef6": 0,
    "Tipo": "interior"
  },
  {
    "id": 109,
    "m": "0.8I",
    "coef1": 381,
    "coef2": 347,
    "coef3": 192,
    "coef4": 128,
    "coef5": 0,
    "coef6": 0,
    "Tipo": "interior"
  },
  {
    "id": 110,
    "m": "0.8II",
    "coef1": 387,
    "coef2": 361,
    "coef3": 199,
    "coef4": 133,
    "coef5": 0,
    "coef6": 0,
    "Tipo": "interior"
  },
  {
    "id": 111,
    "m": "0.9I",
    "coef1": 333,
    "coef2": 320,
    "coef3": 158,
    "coef4": 127,
    "coef5": 0,
    "coef6": 0,
    "Tipo": "interior"
  },
  {
    "id": 112,
    "m": "0.9II",
    "coef1": 338,
    "coef2": 330,
    "coef3": 164,
    "coef4": 131,
    "coef5": 0,
    "coef6": 0,
    "Tipo": "interior"
  },
  {
    "id": 113,
    "m": "1I",
    "coef1": 288,
    "coef2": 288,
    "coef3": 126,
    "coef4": 126,
    "coef5": 0,
    "coef6": 0,
    "Tipo": "interior"
  },
  {
    "id": 114,
    "m": "1II",
    "coef1": 292,
    "coef2": 292,
    "coef3": 130,
    "coef4": 130,
    "coef5": 0,
    "coef6": 0,
    "Tipo": "interior"
  },
  {
    "id": 201,
    "m": "0I",
    "coef1": 998,
    "coef2": 516,
    "coef3": 0,
    "coef4": 326,
    "coef5": 630,
    "coef6": 179,
    "Tipo": "Borde1 Lado corto discontinuo"
  },
  {
    "id": 202,
    "m": "0II",
    "coef1": 1018,
    "coef2": 544,
    "coef3": 0,
    "coef4": 0,
    "coef5": 668,
    "coef6": 187,
    "Tipo": "Borde1 Lado corto discontinuo"
  },
  {
    "id": 203,
    "m": "0.5I",
    "coef1": 568,
    "coef2": 409,
    "coef3": 0,
    "coef4": 258,
    "coef5": 329,
    "coef6": 142,
    "Tipo": "Borde1 Lado corto discontinuo"
  },
  {
    "id": 204,
    "m": "0.5II",
    "coef1": 594,
    "coef2": 431,
    "coef3": 0,
    "coef4": 0,
    "coef5": 356,
    "coef6": 149,
    "Tipo": "Borde1 Lado corto discontinuo"
  },
  {
    "id": 205,
    "m": "0.6I",
    "coef1": 506,
    "coef2": 391,
    "coef3": 0,
    "coef4": 248,
    "coef5": 292,
    "coef6": 137,
    "Tipo": "Borde1 Lado corto discontinuo"
  },
  {
    "id": 206,
    "m": "0.6II",
    "coef1": 533,
    "coef2": 412,
    "coef3": 0,
    "coef4": 0,
    "coef5": 306,
    "coef6": 143,
    "Tipo": "Borde1 Lado corto discontinuo"
  },
  {
    "id": 207,
    "m": "0.7I",
    "coef1": 451,
    "coef2": 372,
    "coef3": 0,
    "coef4": 236,
    "coef5": 240,
    "coef6": 133,
    "Tipo": "Borde1 Lado corto discontinuo"
  },
  {
    "id": 208,
    "m": "0.7II",
    "coef1": 478,
    "coef2": 392,
    "coef3": 0,
    "coef4": 0,
    "coef5": 261,
    "coef6": 141,
    "Tipo": "Borde1 Lado corto discontinuo"
  },
  {
    "id": 209,
    "m": "0.8I",
    "coef1": 403,
    "coef2": 350,
    "coef3": 0,
    "coef4": 222,
    "coef5": 202,
    "coef6": 131,
    "Tipo": "Borde1 Lado corto discontinuo"
  },
  {
    "id": 210,
    "m": "0.8II",
    "coef1": 431,
    "coef2": 369,
    "coef3": 0,
    "coef4": 0,
    "coef5": 219,
    "coef6": 137,
    "Tipo": "Borde1 Lado corto discontinuo"
  },
  {
    "id": 211,
    "m": "0.9I",
    "coef1": 357,
    "coef2": 326,
    "coef3": 0,
    "coef4": 206,
    "coef5": 167,
    "coef6": 129,
    "Tipo": "Borde1 Lado corto discontinuo"
  },
  {
    "id": 212,
    "m": "0.9II",
    "coef1": 388,
    "coef2": 341,
    "coef3": 0,
    "coef4": 0,
    "coef5": 181,
    "coef6": 136,
    "Tipo": "Borde1 Lado corto discontinuo"
  },
  {
    "id": 213,
    "m": "1I",
    "coef1": 315,
    "coef2": 297,
    "coef3": 0,
    "coef4": 190,
    "coef5": 133,
    "coef6": 129,
    "Tipo": "Borde1 Lado corto discontinuo"
  },
  {
    "id": 214,
    "m": "1II",
    "coef1": 346,
    "coef2": 311,
    "coef3": 0,
    "coef4": 0,
    "coef5": 144,
    "coef6": 135,
    "Tipo": "Borde1 Lado corto discontinuo"
  },
  {
    "id": 301,
    "m": "0I",
    "coef1": 1060,
    "coef2": 587,
    "coef3": 651,
    "coef4": 0,
    "coef5": 751,
    "coef6": 185,
    "Tipo": "Borde1 Lado largo discontinuo"
  },
  {
    "id": 302,
    "m": "0II",
    "coef1": 1143,
    "coef2": 687,
    "coef3": 0,
    "coef4": 0,
    "coef5": 912,
    "coef6": 200,
    "Tipo": "Borde1 Lado largo discontinuo"
  },
  {
    "id": 303,
    "m": "0.5I",
    "coef1": 583,
    "coef2": 465,
    "coef3": 362,
    "coef4": 0,
    "coef5": 334,
    "coef6": 147,
    "Tipo": "Borde1 Lado largo discontinuo"
  },
  {
    "id": 304,
    "m": "0.5II",
    "coef1": 624,
    "coef2": 545,
    "coef3": 0,
    "coef4": 0,
    "coef5": 366,
    "coef6": 158,
    "Tipo": "Borde1 Lado largo discontinuo"
  },
  {
    "id": 305,
    "m": "0.6I",
    "coef1": 514,
    "coef2": 442,
    "coef3": 321,
    "coef4": 0,
    "coef5": 285,
    "coef6": 142,
    "Tipo": "Borde1 Lado largo discontinuo"
  },
  {
    "id": 306,
    "m": "0.6II",
    "coef1": 548,
    "coef2": 513,
    "coef3": 0,
    "coef4": 0,
    "coef5": 312,
    "coef6": 153,
    "Tipo": "Borde1 Lado largo discontinuo"
  },
  {
    "id": 307,
    "m": "0.7I",
    "coef1": 453,
    "coef2": 411,
    "coef3": 283,
    "coef4": 0,
    "coef5": 241,
    "coef6": 138,
    "Tipo": "Borde1 Lado largo discontinuo"
  },
  {
    "id": 308,
    "m": "0.7II",
    "coef1": 481,
    "coef2": 470,
    "coef3": 0,
    "coef4": 0,
    "coef5": 263,
    "coef6": 149,
    "Tipo": "Borde1 Lado largo discontinuo"
  },
  {
    "id": 309,
    "m": "0.8I",
    "coef1": 397,
    "coef2": 379,
    "coef3": 250,
    "coef4": 0,
    "coef5": 202,
    "coef6": 135,
    "Tipo": "Borde1 Lado largo discontinuo"
  },
  {
    "id": 310,
    "m": "0.8II",
    "coef1": 420,
    "coef2": 426,
    "coef3": 0,
    "coef4": 0,
    "coef5": 218,
    "coef6": 146,
    "Tipo": "Borde1 Lado largo discontinuo"
  },
  {
    "id": 311,
    "m": "0.9I",
    "coef1": 346,
    "coef2": 347,
    "coef3": 219,
    "coef4": 0,
    "coef5": 164,
    "coef6": 134,
    "Tipo": "Borde1 Lado largo discontinuo"
  },
  {
    "id": 312,
    "m": "0.9II",
    "coef1": 364,
    "coef2": 384,
    "coef3": 0,
    "coef4": 0,
    "coef5": 175,
    "coef6": 145,
    "Tipo": "Borde1 Lado largo discontinuo"
  },
  {
    "id": 313,
    "m": "1I",
    "coef1": 297,
    "coef2": 315,
    "coef3": 190,
    "coef4": 0,
    "coef5": 129,
    "coef6": 133,
    "Tipo": "Borde1 Lado largo discontinuo"
  },
  {
    "id": 314,
    "m": "1II",
    "coef1": 311,
    "coef2": 346,
    "coef3": 0,
    "coef4": 0,
    "coef5": 135,
    "coef6": 144,
    "Tipo": "Borde1 Lado largo discontinuo"
  },
  {
    "id": 401,
    "m": "0I",
    "coef1": 1060,
    "coef2": 600,
    "coef3": 651,
    "coef4": 326,
    "coef5": 751,
    "coef6": 191,
    "Tipo": "Esquina"
  },
  {
    "id": 402,
    "m": "0II",
    "coef1": 1143,
    "coef2": 713,
    "coef3": 0,
    "coef4": 0,
    "coef5": 912,
    "coef6": 212,
    "Tipo": "Esquina"
  },
  {
    "id": 403,
    "m": "0.5I",
    "coef1": 598,
    "coef2": 475,
    "coef3": 362,
    "coef4": 258,
    "coef5": 358,
    "coef6": 152,
    "Tipo": "Esquina"
  },
  {
    "id": 404,
    "m": "0.5II",
    "coef1": 653,
    "coef2": 564,
    "coef3": 0,
    "coef4": 0,
    "coef5": 416,
    "coef6": 168,
    "Tipo": "Esquina"
  },
  {
    "id": 405,
    "m": "0.6I",
    "coef1": 530,
    "coef2": 455,
    "coef3": 321,
    "coef4": 248,
    "coef5": 306,
    "coef6": 146,
    "Tipo": "Esquina"
  },
  {
    "id": 406,
    "m": "0.6II",
    "coef1": 582,
    "coef2": 541,
    "coef3": 0,
    "coef4": 0,
    "coef5": 354,
    "coef6": 163,
    "Tipo": "Esquina"
  },
  {
    "id": 407,
    "m": "0.7I",
    "coef1": 471,
    "coef2": 429,
    "coef3": 277,
    "coef4": 236,
    "coef5": 259,
    "coef6": 142,
    "Tipo": "Esquina"
  },
  {
    "id": 408,
    "m": "0.7II",
    "coef1": 520,
    "coef2": 506,
    "coef3": 0,
    "coef4": 0,
    "coef5": 298,
    "coef6": 158,
    "Tipo": "Esquina"
  },
  {
    "id": 409,
    "m": "0.8I",
    "coef1": 419,
    "coef2": 394,
    "coef3": 250,
    "coef4": 222,
    "coef5": 216,
    "coef6": 140,
    "Tipo": "Esquina"
  },
  {
    "id": 410,
    "m": "0.8II",
    "coef1": 464,
    "coef2": 457,
    "coef3": 0,
    "coef4": 0,
    "coef5": 247,
    "coef6": 156,
    "Tipo": "Esquina"
  },
  {
    "id": 411,
    "m": "0.9I",
    "coef1": 371,
    "coef2": 360,
    "coef3": 219,
    "coef4": 206,
    "coef5": 176,
    "coef6": 138,
    "Tipo": "Esquina"
  },
  {
    "id": 412,
    "m": "0.9II",
    "coef1": 412,
    "coef2": 410,
    "coef3": 0,
    "coef4": 0,
    "coef5": 199,
    "coef6": 154,
    "Tipo": "Esquina"
  },
  {
    "id": 413,
    "m": "1I",
    "coef1": 324,
    "coef2": 324,
    "coef3": 190,
    "coef4": 190,
    "coef5": 137,
    "coef6": 137,
    "Tipo": "Esquina"
  },
  {
    "id": 414,
    "m": "1II",
    "coef1": 364,
    "coef2": 364,
    "coef3": 0,
    "coef4": 0,
    "coef5": 153,
    "coef6": 153,
    "Tipo": "Esquina"
  },
  {
    "id": 501,
    "m": "0I",
    "coef1": 1060,
    "coef2": 0,
    "coef3": 651,
    "coef4": 220,
    "coef5": 751,
    "coef6": 185,
    "Tipo": "Extremo 1 Lado largo continuo"
  },
  {
    "id": 502,
    "m": "0II",
    "coef1": 1143,
    "coef2": 0,
    "coef3": 0,
    "coef4": 0,
    "coef5": 912,
    "coef6": 200,
    "Tipo": "Extremo 1 Lado largo continuo"
  },
  {
    "id": 503,
    "m": "0.5I",
    "coef1": 970,
    "coef2": 0,
    "coef3": 370,
    "coef4": 220,
    "coef5": 730,
    "coef6": 430,
    "Tipo": "Extremo 1 Lado largo continuo"
  },
  {
    "id": 504,
    "m": "0.5II",
    "coef1": 1070,
    "coef2": 0,
    "coef3": 0,
    "coef4": 0,
    "coef5": 800,
    "coef6": 520,
    "Tipo": "Extremo 1 Lado largo continuo"
  },
  {
    "id": 505,
    "m": "0.6I",
    "coef1": 890,
    "coef2": 0,
    "coef3": 340,
    "coef4": 220,
    "coef5": 670,
    "coef6": 430,
    "Tipo": "Extremo 1 Lado largo continuo"
  },
  {
    "id": 506,
    "m": "0.6II",
    "coef1": 1010,
    "coef2": 0,
    "coef3": 0,
    "coef4": 0,
    "coef5": 760,
    "coef6": 520,
    "Tipo": "Extremo 1 Lado largo continuo"
  },
  {
    "id": 507,
    "m": "0.7I",
    "coef1": 810,
    "coef2": 0,
    "coef3": 310,
    "coef4": 220,
    "coef5": 610,
    "coef6": 430,
    "Tipo": "Extremo 1 Lado largo continuo"
  },
  {
    "id": 508,
    "m": "0.7II",
    "coef1": 940,
    "coef2": 0,
    "coef3": 0,
    "coef4": 0,
    "coef5": 710,
    "coef6": 520,
    "Tipo": "Extremo 1 Lado largo continuo"
  },
  {
    "id": 509,
    "m": "0.8I",
    "coef1": 730,
    "coef2": 0,
    "coef3": 280,
    "coef4": 220,
    "coef5": 550,
    "coef6": 430,
    "Tipo": "Extremo 1 Lado largo continuo"
  },
  {
    "id": 510,
    "m": "0.8II",
    "coef1": 870,
    "coef2": 0,
    "coef3": 0,
    "coef4": 0,
    "coef5": 650,
    "coef6": 520,
    "Tipo": "Extremo 1 Lado largo continuo"
  },
  {
    "id": 511,
    "m": "0.9I",
    "coef1": 650,
    "coef2": 0,
    "coef3": 250,
    "coef4": 220,
    "coef5": 490,
    "coef6": 430,
    "Tipo": "Extremo 1 Lado largo continuo"
  },
  {
    "id": 512,
    "m": "0.9II",
    "coef1": 790,
    "coef2": 0,
    "coef3": 0,
    "coef4": 0,
    "coef5": 600,
    "coef6": 520,
    "Tipo": "Extremo 1 Lado largo continuo"
  },
  {
    "id": 513,
    "m": "1I",
    "coef1": 570,
    "coef2": 0,
    "coef3": 220,
    "coef4": 220,
    "coef5": 430,
    "coef6": 430,
    "Tipo": "Extremo 1 Lado largo continuo"
  },
  {
    "id": 514,
    "m": "1II",
    "coef1": 710,
    "coef2": 0,
    "coef3": 0,
    "coef4": 0,
    "coef5": 540,
    "coef6": 520,
    "Tipo": "Extremo 1 Lado largo continuo"
  },
  {
    "id": 601,
    "m": "0I",
    "coef1": 0,
    "coef2": 570,
    "coef3": 570,
    "coef4": 330,
    "coef5": 1100,
    "coef6": 200,
    "Tipo": "Extremo 1 Lado corto continuo"
  },
  {
    "id": 602,
    "m": "0II",
    "coef1": 0,
    "coef2": 710,
    "coef3": 0,
    "coef4": 0,
    "coef5": 1670,
    "coef6": 250,
    "Tipo": "Extremo 1 Lado corto continuo"
  },
  {
    "id": 603,
    "m": "0.5I",
    "coef1": 0,
    "coef2": 570,
    "coef3": 480,
    "coef4": 220,
    "coef5": 960,
    "coef6": 430,
    "Tipo": "Extremo 1 Lado corto continuo"
  },
  {
    "id": 604,
    "m": "0.5II",
    "coef1": 0,
    "coef2": 710,
    "coef3": 0,
    "coef4": 0,
    "coef5": 1060,
    "coef6": 540,
    "Tipo": "Extremo 1 Lado corto continuo"
  },
  {
    "id": 605,
    "m": "0.6I",
    "coef1": 0,
    "coef2": 570,
    "coef3": 420,
    "coef4": 220,
    "coef5": 840,
    "coef6": 430,
    "Tipo": "Extremo 1 Lado corto continuo"
  },
  {
    "id": 606,
    "m": "0.6II",
    "coef1": 0,
    "coef2": 710,
    "coef3": 0,
    "coef4": 0,
    "coef5": 950,
    "coef6": 540,
    "Tipo": "Extremo 1 Lado corto continuo"
  },
  {
    "id": 607,
    "m": "0.7I",
    "coef1": 0,
    "coef2": 570,
    "coef3": 370,
    "coef4": 220,
    "coef5": 730,
    "coef6": 430,
    "Tipo": "Extremo 1 Lado corto continuo"
  },
  {
    "id": 608,
    "m": "0.7II",
    "coef1": 0,
    "coef2": 710,
    "coef3": 0,
    "coef4": 0,
    "coef5": 850,
    "coef6": 540,
    "Tipo": "Extremo 1 Lado corto continuo"
  },
  {
    "id": 609,
    "m": "0.8I",
    "coef1": 0,
    "coef2": 570,
    "coef3": 310,
    "coef4": 220,
    "coef5": 620,
    "coef6": 430,
    "Tipo": "Extremo 1 Lado corto continuo"
  },
  {
    "id": 610,
    "m": "0.8II",
    "coef1": 0,
    "coef2": 710,
    "coef3": 0,
    "coef4": 0,
    "coef5": 740,
    "coef6": 540,
    "Tipo": "Extremo 1 Lado corto continuo"
  },
  {
    "id": 611,
    "m": "0.9I",
    "coef1": 0,
    "coef2": 570,
    "coef3": 270,
    "coef4": 220,
    "coef5": 540,
    "coef6": 430,
    "Tipo": "Extremo 1 Lado corto continuo"
  },
  {
    "id": 612,
    "m": "0.9II",
    "coef1": 0,
    "coef2": 710,
    "coef3": 0,
    "coef4": 0,
    "coef5": 660,
    "coef6": 540,
    "Tipo": "Extremo 1 Lado corto continuo"
  },
  {
    "id": 613,
    "m": "1I",
    "coef1": 0,
    "coef2": 570,
    "coef3": 220,
    "coef4": 220,
    "coef5": 430,
    "coef6": 430,
    "Tipo": "Extremo 1 Lado corto continuo"
  },
  {
    "id": 614,
    "m": "1II",
    "coef1": 0,
    "coef2": 710,
    "coef3": 0,
    "coef4": 0,
    "coef5": 520,
    "coef6": 540,
    "Tipo": "Extremo 1 Lado corto continuo"
  },
  {
    "id": 701,
    "m": "0I",
    "coef1": 570,
    "coef2": 330,
    "coef3": 110,
    "coef4": 200,
    "coef5": 0,
    "coef6": 0,
    "Tipo": "Aislado"
  },
  {
    "id": 702,
    "m": "0II",
    "coef1": 0,
    "coef2": 0,
    "coef3": 1670,
    "coef4": 250,
    "coef5": 0,
    "coef6": 0,
    "Tipo": "Aislado"
  },
  {
    "id": 703,
    "m": "0.5I",
    "coef1": 550,
    "coef2": 330,
    "coef3": 830,
    "coef4": 500,
    "coef5": 0,
    "coef6": 0,
    "Tipo": "Aislado"
  },
  {
    "id": 704,
    "m": "0.5II",
    "coef1": 0,
    "coef2": 0,
    "coef3": 1380,
    "coef4": 830,
    "coef5": 0,
    "coef6": 0,
    "Tipo": "Aislado"
  },
  {
    "id": 705,
    "m": "0.6I",
    "coef1": 530,
    "coef2": 330,
    "coef3": 800,
    "coef4": 500,
    "coef5": 0,
    "coef6": 0,
    "Tipo": "Aislado"
  },
  {
    "id": 706,
    "m": "0.6II",
    "coef1": 0,
    "coef2": 0,
    "coef3": 1330,
    "coef4": 830,
    "coef5": 0,
    "coef6": 0,
    "Tipo": "Aislado"
  },
  {
    "id": 707,
    "m": "0.7I",
    "coef1": 470,
    "coef2": 330,
    "coef3": 720,
    "coef4": 500,
    "coef5": 0,
    "coef6": 0,
    "Tipo": "Aislado"
  },
  {
    "id": 708,
    "m": "0.7II",
    "coef1": 0,
    "coef2": 0,
    "coef3": 1190,
    "coef4": 830,
    "coef5": 0,
    "coef6": 0,
    "Tipo": "Aislado"
  },
  {
    "id": 709,
    "m": "0.8I",
    "coef1": 430,
    "coef2": 330,
    "coef3": 640,
    "coef4": 500,
    "coef5": 0,
    "coef6": 0,
    "Tipo": "Aislado"
  },
  {
    "id": 710,
    "m": "0.8II",
    "coef1": 0,
    "coef2": 0,
    "coef3": 1070,
    "coef4": 830,
    "coef5": 0,
    "coef6": 0,
    "Tipo": "Aislado"
  },
  {
    "id": 711,
    "m": "0.9I",
    "coef1": 380,
    "coef2": 330,
    "coef3": 570,
    "coef4": 500,
    "coef5": 0,
    "coef6": 0,
    "Tipo": "Aislado"
  },
  {
    "id": 712,
    "m": "0.9II",
    "coef1": 0,
    "coef2": 0,
    "coef3": 950,
    "coef4": 830,
    "coef5": 0,
    "coef6": 0,
    "Tipo": "Aislado"
  },
  {
    "id": 713,
    "m": "1I",
    "coef1": 330,
    "coef2": 330,
    "coef3": 500,
    "coef4": 500,
    "coef5": 0,
    "coef6": 0,
    "Tipo": "Aislado"
  },
  {
    "id": 714,
    "m": "1II",
    "coef1": 0,
    "coef2": 0,
    "coef3": 830,
    "coef4": 830,
    "coef5": 0,
    "coef6": 0,
    "Tipo": "Aislado"
  }
]